belief_state_superposition-0.1.0.dist-info/METADATA
belief_state_superposition-0.1.0.dist-info/WHEEL
belief_state_superposition/__init__.py
belief_state_superposition/data.py
belief_state_superposition/hmm.py
belief_state_superposition/model.py
belief_state_superposition/train.py
belief_state_superposition-0.1.0.dist-info/RECORD
