Metadata-Version: 2.1
Name: belief-state-superposition
Version: 0.1.0
Summary: Investigating belief state representations of transformers trained on Hidden Markov Model emissions
Author-Email: Daniel Tan <dtch1997@users.noreply.github.com>, Daniel CH Tan <dtch1997@users.noreply.github.com>
License: MIT
Requires-Python: >=3.10
Requires-Dist: transformer-lens>=1.17.0
Requires-Dist: ipykernel>=6.29.4
Requires-Dist: eindex-callum>=0.1.1
Requires-Dist: pre-commit>=3.7.1
Requires-Dist: ruff>=0.4.3
Requires-Dist: pytest>=8.2.0
Requires-Dist: pyright>=1.1.361
